LICENSE
MANIFEST.in
README.rst
setup.cfg
setup.py
django_yaat.egg-info/PKG-INFO
django_yaat.egg-info/SOURCES.txt
django_yaat.egg-info/dependency_links.txt
django_yaat.egg-info/not-zip-safe
django_yaat.egg-info/requires.txt
django_yaat.egg-info/top_level.txt
yaat/__init__.py
yaat/forms.py
yaat/meta.py
yaat/models.py
yaat/resource.py
yaat/migrations/0001_initial.py
yaat/migrations/0002_auto_20151102_0814.py
yaat/migrations/__init__.py