Metadata-Version: 1.0
Name: django-yaat
Version: 1.4.4
Summary: The django-restify-framework resource of the yaat AngularJs module
Home-page: https://github.com/slapec/django-yaat
Author: Slapec
Author-email: UNKNOWN
License: MIT
Platform: UNKNOWN
